tadoc/__init__.py
tadoc-0.2.dist-info/LICENSE
tadoc-0.2.dist-info/WHEEL
tadoc-0.2.dist-info/METADATA
tadoc-0.2.dist-info/RECORD
