Metadata-Version: 2.1
Name: tadoc
Version: 0.2
Summary: Get TaLib Structure Func Doc
Author-email: yvictor <yvictor3141@gmail.com>
Classifier: License :: OSI Approved :: MIT License
Project-URL: Home, https://github.com/Yvictor/tadoc
